stackit/serverbackup/__init__.py
stackit/serverbackup/api/__init__.py
stackit/serverbackup/api/default_api.py
stackit/serverbackup/api_client.py
stackit/serverbackup/api_response.py
stackit/serverbackup/configuration.py
stackit/serverbackup/exceptions.py
stackit/serverbackup/models/__init__.py
stackit/serverbackup/models/backup.py
stackit/serverbackup/models/backup_job.py
stackit/serverbackup/models/backup_policy.py
stackit/serverbackup/models/backup_policy_backup_properties.py
stackit/serverbackup/models/backup_properties.py
stackit/serverbackup/models/backup_schedule.py
stackit/serverbackup/models/backup_volume_backups_inner.py
stackit/serverbackup/models/create_backup_payload.py
stackit/serverbackup/models/create_backup_schedule_payload.py
stackit/serverbackup/models/enable_service_resource_payload.py
stackit/serverbackup/models/error_response.py
stackit/serverbackup/models/get_backup_policies_response.py
stackit/serverbackup/models/get_backup_schedules_response.py
stackit/serverbackup/models/get_backup_service_response.py
stackit/serverbackup/models/get_backups_list_response.py
stackit/serverbackup/models/restore_backup_payload.py
stackit/serverbackup/models/restore_volume_backup_payload.py
stackit/serverbackup/models/update_backup_schedule_payload.py
stackit/serverbackup/py.typed
stackit/serverbackup/rest.py
stackit_serverbackup-1.1.1.dist-info/METADATA
stackit_serverbackup-1.1.1.dist-info/WHEEL
stackit_serverbackup-1.1.1.dist-info/licenses/LICENSE.md
stackit_serverbackup-1.1.1.dist-info/licenses/NOTICE.txt
stackit_serverbackup-1.1.1.dist-info/RECORD
